README.md
setup.py
data2struct/__init__.py
data2struct/data2struct.py
data2struct.egg-info/PKG-INFO
data2struct.egg-info/SOURCES.txt
data2struct.egg-info/dependency_links.txt
data2struct.egg-info/not-zip-safe
data2struct.egg-info/top_level.txt