Metadata-Version: 1.0
Name: data2struct
Version: 1.0
Summary: Base functions for various x2struct tools.
Home-page: https://github.com/jalavosus/data2struct
Author: jalavosus
Author-email: alavosus.james@gmail.com
License: MIT
Platform: UNKNOWN
